{
  "docusaurus-plugin-content-docs": {
    "default": {
      "loadedVersions": [
        {
          "versionName": "current",
          "label": "Next",
          "banner": null,
          "badge": false,
          "noIndex": false,
          "className": "docs-version-current",
          "path": "/",
          "tagsPath": "/tags",
          "isLast": true,
          "routePriority": -1,
          "sidebarFilePath": "/Users/mac/buidler-documentation/sidebars.js",
          "contentPath": "/Users/mac/buidler-documentation/general",
          "contentPathLocalized": "/Users/mac/buidler-documentation/i18n/en/docusaurus-plugin-content-docs/current",
          "docs": [
            {
              "unversionedId": "about",
              "id": "about",
              "title": "About Buidler",
              "description": "Buidler is a messaging platform lets you dive into communities right on the sites you're browsing, instantly.",
              "source": "@site/general/buidler-introduction.mdx",
              "sourceDirName": ".",
              "slug": "/about",
              "permalink": "/about",
              "draft": false,
              "tags": [],
              "version": "current",
              "sidebarPosition": 1,
              "frontMatter": {
                "title": "About Buidler",
                "sidebar_position": 1,
                "id": "about",
                "description": "Buidler is a messaging platform lets you dive into communities right on the sites you're browsing, instantly."
              },
              "sidebar": "tutorialSidebar",
              "next": {
                "title": "Add Community Chat Plugin",
                "permalink": "/add-community-chat-plugin"
              }
            },
            {
              "unversionedId": "add-community-chat-plugin",
              "id": "add-community-chat-plugin",
              "title": "Add Community Chat Plugin",
              "description": "Website owners can increase user engagement by integrating our plugin. Seamlessly offer real-time support and connect with your audience. Strengthen user loyalty, attract new visitors, and grow your community organically.",
              "source": "@site/general/add-community-chat-plugin.mdx",
              "sourceDirName": ".",
              "slug": "/add-community-chat-plugin",
              "permalink": "/add-community-chat-plugin",
              "draft": false,
              "tags": [],
              "version": "current",
              "sidebarPosition": 1,
              "frontMatter": {
                "title": "Add Community Chat Plugin",
                "sidebar_position": 1,
                "id": "add-community-chat-plugin",
                "description": "Website owners can increase user engagement by integrating our plugin. Seamlessly offer real-time support and connect with your audience. Strengthen user loyalty, attract new visitors, and grow your community organically.",
                "image": "https://docs.buidler.app/img/buidler-extension.png",
                "og:image": "https://docs.buidler.app/img/buidler-extension.png",
                "og:title": "Add Community Chat To Your Website",
                "og:description": "Website owners can increase user engagement by integrating our plugin. Seamlessly offer real-time support and connect with your audience. Strengthen user loyalty, attract new visitors, and grow your community organically.",
                "og:twitter:card": "summary_large_image",
                "og:twitter:site": "@buidler_app",
                "og:twitter:title": "Add Community Chat To Your Website",
                "og:twitter:description": "Website owners can increase user engagement by integrating our plugin. Seamlessly offer real-time support and connect with your audience. Strengthen user loyalty, attract new visitors, and grow your community organically.",
                "og:twitter:image": "https://docs.buidler.app/img/buidler-extension.png"
              },
              "sidebar": "tutorialSidebar",
              "previous": {
                "title": "About Buidler",
                "permalink": "/about"
              }
            }
          ],
          "drafts": [],
          "sidebars": {
            "tutorialSidebar": [
              {
                "type": "doc",
                "id": "about"
              },
              {
                "type": "doc",
                "id": "add-community-chat-plugin"
              }
            ]
          }
        }
      ]
    }
  },
  "docusaurus-plugin-content-blog": {
    "default": {
      "blogSidebarTitle": "Recent posts",
      "blogPosts": [],
      "blogListPaginated": [],
      "blogTags": {},
      "blogTagsListPath": "/blog/tags",
      "blogTagsPaginated": []
    }
  },
  "docusaurus-plugin-content-pages": {
    "default": [
      {
        "type": "jsx",
        "permalink": "/404",
        "source": "@site/src/pages/404.js"
      },
      {
        "type": "jsx",
        "permalink": "/",
        "source": "@site/src/pages/index.js"
      },
      {
        "type": "mdx",
        "permalink": "/markdown-page",
        "source": "@site/src/pages/markdown-page.md",
        "title": "Markdown page example",
        "description": "You don't need React to write simple standalone pages.",
        "frontMatter": {
          "title": "Markdown page example"
        }
      }
    ]
  },
  "docusaurus-plugin-debug": {},
  "docusaurus-theme-classic": {},
  "docusaurus-theme-search-algolia": {},
  "buidler-plugin": {},
  "docusaurus-plugin-image-zoom": {},
  "docusaurus-bootstrap-plugin": {},
  "docusaurus-mdx-fallback-plugin": {}
}